gan_pytorch/__init__.py
gan_pytorch/model.py
gan_pytorch/utils.py
utils/__init__.py
utils/inception_score.py
utils/utils.py
gan_pytorch-0.4.0.dist-info/LICENSE
gan_pytorch-0.4.0.dist-info/METADATA
gan_pytorch-0.4.0.dist-info/WHEEL
gan_pytorch-0.4.0.dist-info/top_level.txt
gan_pytorch-0.4.0.dist-info/RECORD
